odoo/addons/base_multi_branch_company/README.rst
odoo/addons/base_multi_branch_company/__init__.py
odoo/addons/base_multi_branch_company/__manifest__.py
odoo/addons/base_multi_branch_company/i18n/base_multi_branch_company.pot
odoo/addons/base_multi_branch_company/models/__init__.py
odoo/addons/base_multi_branch_company/models/res_branch.py
odoo/addons/base_multi_branch_company/models/res_company.py
odoo/addons/base_multi_branch_company/readme/CONTRIBUTORS.rst
odoo/addons/base_multi_branch_company/readme/DESCRIPTION.rst
odoo/addons/base_multi_branch_company/readme/USAGE.rst
odoo/addons/base_multi_branch_company/security/ir.model.access.csv
odoo/addons/base_multi_branch_company/static/description/icon.png
odoo/addons/base_multi_branch_company/static/description/index.html
odoo/addons/base_multi_branch_company/views/res_branch_view.xml
odoo/addons/base_multi_branch_company/views/res_company.xml
odoo_addon_base_multi_branch_company-15.0.1.0.0.2.dist-info/METADATA
odoo_addon_base_multi_branch_company-15.0.1.0.0.2.dist-info/WHEEL
odoo_addon_base_multi_branch_company-15.0.1.0.0.2.dist-info/top_level.txt
odoo_addon_base_multi_branch_company-15.0.1.0.0.2.dist-info/RECORD
